noseselecttests/__init__.py
noseselecttests/tests.py
nose_selecttests-0.5.dist-info/top_level.txt
nose_selecttests-0.5.dist-info/entry_points.txt
nose_selecttests-0.5.dist-info/METADATA
nose_selecttests-0.5.dist-info/DESCRIPTION.rst
nose_selecttests-0.5.dist-info/metadata.json
nose_selecttests-0.5.dist-info/WHEEL
nose_selecttests-0.5.dist-info/RECORD
