Metadata-Version: 2.0
Name: nose-selecttests
Version: 0.5
Summary: Specify whitelist of keywords for tests to be run by nose
Home-page: http://github.com/iElectric/nose-selecttests/
Author: Domen Kozar
Author-email: domen@dev.si
License: BSD
Platform: UNKNOWN
Requires-Dist: nose
Requires-Dist: six
